{
  "Home": "Cartref",
  "Premade": "Rhagosodedig",
  "Custom": "Addasedig",
  "Adaptive": "Addasol",
  "Games": "Gemau",
  "Auto": "Awtomatig",
  "Info": "Gwybodaeth",
  "Settings": "Gosodiadau",
  "Overlay": "Troshaen",
  "Buy us a beer! ♥": "Prynwch gwrw i ni! ♥",
  "Join our Discord!": "Ymunwch â'n Discord!",
  "Close Application": "Cau'r Rhaglen",
  "Welcome To": "Croeso i",
  "Try Out The Premade Presets": "Rhowch gynnig ar y rhagosodiadau",
  "Created and maintained by JamesCJ, with contributions from the wider community": "Crëwyd a chynhelir gan JamesCJ, gyda chyfraniadau gan y gymuned ehangach",
  "Premade Presets": "Rhagosodiadau Parod",
  "Custom Presets": "Rhagosodiadau Addasedig",
  "Adaptive Mode": "Modd Addasol",
  "Automations": "Awtomeiddiadau",
  "Game Library": "Llyfrgell Gemau",
  "System Info": "Gwybodaeth System",
  "Need Help?": "Angen Cymorth?",
  "Support Us": "Cefnogwch Ni",
  "Choose a tuning profile and review the commands before applying it.": "Dewiswch broffil tiwnio ac adolygwch y gorchmynion cyn ei gymhwyso.",
  "Performance Preset": "Rhagosodiad Perfformiad",
  "UXTU Command Output:": "Allbwn Gorchymyn UXTU:",
  "Eco": "Economaidd",
  "Balanced": "Cytbwys",
  "Performance": "Perfformiad",
  "Extreme": "Eithafol",
  "Create, edit and apply a hardware tuning preset. Enable only the settings that should be included.": "Crëwch, golygwch a chymhwyswch ragosodiad tiwnio caledwedd. Galluogwch y gosodiadau sydd i'w cynnwys yn unig.",
  "Saved Presets:": "Rhagosodiadau wedi'u cadw:",
  "New Preset Name:": "Enw rhagosodiad newydd:",
  "APU Temperature Tuning": "Tiwnio Tymheredd APU",
  "CPU Temperature Tuning": "Tiwnio Tymheredd CPU",
  "APU Power Tuning": "Tiwnio Pŵer APU",
  "CPU Power Tuning": "Tiwnio Pŵer CPU",
  "APU VRM Tuning": "Tiwnio Modiwl Rheoleiddiwr Foltedd (VRM) APU",
  "iGPU Tuning": "Tiwnio iGPU",
  "Radeon™ Graphics Options": "Dewisiadau Graffeg Radeon™",
  "NVIDIA GPU Tuning": "Tiwnio GPU NVIDIA",
  "Intel Power Balance": "Cydbwysedd Pŵer Intel",
  "Intel Clock Ratio Control": "Rheoli Cymhareb Cloc Intel",
  "Intel FIVR Tuning": "Tiwnio Rheoleiddiwr Foltedd Cwbl Integredig (FIVR) Intel",
  "AMD Ryzen™ CPU Tuning": "Tiwnio CPU AMD Ryzen™",
  "AMD Precision Boost Overdrive": "AMD Precision Boost Overdrive",
  "AMD Curve Optimiser": "Optimeiddiwr Cromlin AMD",
  "Core Complex Die (CCD) Affinity Mode": "Modd Perthynas Core Complex Die (CCD)",
  "Display Refresh Rate": "Cyfradd Adnewyddu'r Dangosydd",
  "Windows Power Mode": "Modd Pŵer Windows",
  "Undo overclock settings": "Dadwneud gosodiadau gor-glocio",
  "Reload settings of current preset values": "Ail-lwytho gwerthoedd y rhagosodiad cyfredol",
  "Delete current settings preset": "Dileu rhagosodiad cyfredol",
  "Save current settings as new preset": "Cadw'r gosodiadau cyfredol fel rhagosodiad newydd",
  "Apply current settings": "Cymhwyso'r gosodiadau cyfredol",
  "Apply presets automatically when power or system state changes.": "Cymhwyswch ragosodiadau'n awtomatig pan fydd cyflwr pŵer neu'r system yn newid.",
  "Preset on Battery Charge": "Rhagosodiad wrth Wefru'r Batri",
  "Preset on Battery Discharge": "Rhagosodiad wrth Ddadwefru'r Batri",
  "Preset on System Resume": "Rhagosodiad wrth Ailddechrau'r System",
  "Refresh the preset list": "Adnewyddu'r rhestr rhagosodiadau",
  "Game Library": "Llyfrgell Gemau",
  "Launch tracked games and review their recorded performance data.": "Lansiwch gemau a dracir ac adolygwch eu data perfformiad.",
  "Average FPS": "Fframiau yr Eiliad (FPS) ar Gyfartaledd",
  "Average Frametime": "Amser Ffrâm Cyfartalog",
  "Game configuration": "Ffurfweddiad gêm",
  "Launch game": "Lansio gêm",
  "No games found": "Ni chanfuwyd gemau",
  "Add a game manually or reload the library.": "Ychwanegwch gêm â llaw neu ail-lwythwch y llyfrgell.",
  "Reload the game library": "Ail-lwytho'r llyfrgell gemau",
  "Add a game manually": "Ychwanegu gêm â llaw",
  "Locating games": "Yn chwilio am gemau",
  "This should only take a few moments.": "Dylai hyn gymryd ychydig eiliadau yn unig.",
  "Game Overlay": "Troshaen Gêm",
  "Configure the click-through performance overlay and its global shortcuts.": "Ffurfweddwch y droshaen perfformiad a'i llwybrau byr byd-eang.",
  "Show overlay": "Dangos y droshaen",
  "Hide overlay": "Cuddio'r droshaen",
  "Save overlay settings": "Cadw gosodiadau'r droshaen",
  "Overlay behaviour": "Ymddygiad y droshaen",
  "Visible information": "Gwybodaeth weladwy",
  "Size and refresh rate": "Maint a chyfradd adnewyddu",
  "Overlay scale": "Graddfa'r droshaen",
  "Panel opacity": "Didreiddedd y panel",
  "Refresh interval": "Cyfnod adnewyddu",
  "Settings": "Gosodiadau",
  "Configure startup behaviour, automation, diagnostics and updates.": "Ffurfweddwch ymddygiad cychwyn, awtomeiddio, diagnosteg a diweddariadau.",
  "Application behaviour": "Ymddygiad y rhaglen",
  "Language": "Iaith",
  "Start on system boot": "Cychwyn wrth gychwyn y system",
  "Start minimised": "Cychwyn wedi'i leihau",
  "Minimise instead of closing": "Lleihau yn lle cau",
  "Reapply settings on start": "Ailgymhwyso gosodiadau wrth gychwyn",
  "Automatically reapply every": "Ailgymhwyso'n awtomatig bob",
  "seconds": "eiliad",
  "Check for updates automatically": "Gwirio am ddiweddariadau'n awtomatig",
  "Start Adaptive Mode automatically": "Cychwyn Modd Addasol yn awtomatig",
  "Track games": "Tracio gemau",
  "Diagnostics": "Diagnosteg",
  "Diagnostic logging": "Cofnodi diagnostig",
  "Off": "I ffwrdd",
  "Error only": "Gwallau yn unig",
  "Debug": "Dadfygio",
  "Start Stress Test": "Cychwyn Prawf Straen",
  "High CPU load": "Llwyth CPU uchel",
  "The stress test places extreme load on the CPU. Ensure cooling is adequate and proceed at your own risk.": "Mae'r prawf straen yn rhoi llwyth eithafol ar y CPU. Sicrhewch fod yr oeri'n ddigonol a pharhewch ar eich menter eich hun.",
  "About Universal x86 Tuning Utility": "Ynghylch Universal x86 Tuning Utility",
  "Check for Updates": "Gwirio am Ddiweddariadau",
  "Download Update": "Lawrlwytho Diweddariad",
  "Review detailed device, processor, memory and battery information.": "Adolygwch wybodaeth fanwl am y ddyfais, prosesydd, cof a batri.",
  "Device Information": "Gwybodaeth Dyfais",
  "Processor Information": "Gwybodaeth Prosesydd",
  "Memory Information": "Gwybodaeth Cof",
  "Battery Information": "Gwybodaeth Batri",
  "Name": "Enw",
  "Producer": "Gwneuthurwr",
  "Model": "Model",
  "Processor": "Prosesydd",
  "Codename": "Enw cod",
  "Cores": "Creiddiau",
  "Threads": "Trywyddau",
  "Base Clock": "Cloc Sylfaen",
  "Health": "Iechyd",
  "Cycles": "Cylchoedd",
  "Capacity": "Cynhwysedd",
  "Charge Rate": "Cyfradd Gwefru",
  "Fan Control": "Rheoli Ffan",
  "Fan configuration": "Ffurfweddiad ffan",
  "Manual fan speed": "Cyflymder ffan â llaw",
  "Reload Config": "Ail-lwytho'r Ffurfweddiad",
  "Test Fan Curve": "Profi Cromlin y Ffan",
  "Update Fan Speed": "Diweddaru Cyflymder y Ffan",
  "Enable Fan Control": "Galluogi Rheoli'r Ffan",
  "Disable Fan Control": "Analluogi Rheoli'r Ffan",
  "Cancel": "Canslo",
  "Install Driver": "Gosod Gyrrwr",
  "Skin Temperature Aware Power Management (STAPM) Limit (W)": "Terfyn Rheoli Pŵer sy'n Ymwybodol o Dymheredd y Croen (STAPM) (W)",
  "Package Power Tracking (PPT) Limit (W)": "Terfyn Tracio Pŵer Pecyn (PPT) (W)",
  "Electrical Design Current (EDC) Limit (A)": "Terfyn Cerrynt Dylunio Trydanol (EDC) (A)",
  "Thermal Design Current (TDC) Limit (A)": "Terfyn Cerrynt Dylunio Thermol (TDC) (A)",
  "Microsoft Visual C++ Redistributable is not installed.\nWould you like to download it now?": "Nid yw Microsoft Visual C++ Redistributable wedi'i osod.\nHoffech chi ei lawrlwytho nawr?",
  "Missing VC Redistributable": "VC Redistributable ar goll",
  "Head to the Phantom Control Centre GitHub releases page to easily download the latest build!": "Ewch i dudalen fersiynau GitHub Phantom Control Centre i lawrlwytho'r fersiwn ddiweddaraf!",
  "An update for Universal x86 Tuning Utility has been found!": "Mae diweddariad ar gyfer Universal x86 Tuning Utility ar gael!",
  "Universal x86 Tuning Utility is up to date!": "Mae Universal x86 Tuning Utility yn gyfredol!",
  "No internet connection!": "Dim cysylltiad rhyngrwyd!",
  "Universal x86 Tuning Utility will close and the installer will open when the download is complete": "Bydd Universal x86 Tuning Utility yn cau a bydd y gosodwr yn agor pan fydd y lawrlwythiad wedi gorffen",
  "Failed to launch MSI: {0}": "Methwyd cychwyn MSI: {0}",
  "Start Adaptive Mode": "Cychwyn Modd Addasol",
  "Stop Adaptive Mode": "Stopio Modd Addasol",
  "Disabled": "Analluog",
  "Enabled - {0}% - {1}°C": "Galluog - {0}% - {1}°C",
  "The overlay settings could not be saved.\n\n{0}": "Ni ellid cadw gosodiadau'r droshaen.\n\n{0}",
  "Overlay settings error": "Gwall gosodiadau'r droshaen",
  "Choose two different shortcuts that each include a non-modifier key.": "Dewiswch ddau lwybr byr gwahanol sydd ill dau'n cynnwys allwedd nad yw'n addasydd.",
  "Invalid overlay shortcut": "Llwybr byr troshaen annilys",
  "Close": "Cau",
  "Downloading the PawnIO driver installer...": "Yn lawrlwytho gosodwr gyrrwr PawnIO...",
  "Installing the PawnIO driver silently. Please wait...": "Yn gosod gyrrwr PawnIO yn dawel. Arhoswch...",
  "Administrator permission is required to install the PawnIO driver.\n\nPlease approve the Windows security prompt to continue.": "Mae angen caniatâd gweinyddwr i osod gyrrwr PawnIO.\n\nCymeradwywch anogwr diogelwch Windows i barhau.",
  "PawnIO driver installation completed successfully.\n\nYou may need to restart the application, or Windows, before all hardware sensors and controls become available.": "Cwblhawyd gosod gyrrwr PawnIO yn llwyddiannus.\n\nEfallai y bydd angen ailgychwyn y rhaglen neu Windows cyn y bydd pob synhwyrydd a rheolydd ar gael.",
  "PawnIO installer exited with code {0}.\n\nThe driver may not have installed correctly. Please try again, or run the installer manually as administrator.": "Daeth gosodwr PawnIO i ben gyda chod {0}.\n\nEfallai na osodwyd y gyrrwr yn gywir. Ceisiwch eto neu rhedwch y gosodwr fel gweinyddwr.",
  "PawnIO driver installation failed.\n\n{0}": "Methodd gosod gyrrwr PawnIO.\n\n{0}",
  "Performance Preset": "Rhagosodiad Perfformiad",
  "Extreme Preset": "Rhagosodiad Eithafol",
  "Eco Preset": "Rhagosodiad Economaidd",
  "Balanced Preset": "Rhagosodiad Cytbwys",
  "Preset Applied": "Rhagosodiad wedi'i Gymhwyso",
  "Preset Saved": "Rhagosodiad wedi'i Gadw",
  "Preset Deleted": "Rhagosodiad wedi'i Ddileu",
  "Your custom preset settings have been applied!": "Mae gosodiadau eich rhagosodiad addasedig wedi'u cymhwyso!",
  "Your preset {0} has been saved successfully!": "Cadwyd eich rhagosodiad {0} yn llwyddiannus!",
  "Your preset {0} has been deleted successfully!": "Dilëwyd eich rhagosodiad {0} yn llwyddiannus!",
  "Launching {0}": "Yn lansio {0}",
  "This preset is optimized for maximum performance by increasing the power limits of the APU/CPU, which allows it to run at higher clock speeds for longer periods of time. This can result in improved system responsiveness and faster load times in applications that require high levels of processing power.": "Mae'r rhagosodiad hwn wedi'i optimeiddio ar gyfer perfformiad uchaf drwy gynyddu terfynau pŵer yr APU/CPU, gan ganiatáu iddo redeg ar gyflymder cloc uwch am gyfnod hirach.",
  "This preset aims to push the power limits of the system to their maximum, allowing for the highest possible performance. This preset is designed for users who demand the most from their hardware and are willing to tolerate higher power consumption and potentially increased noise levels.": "Mae'r rhagosodiad hwn yn gwthio terfynau pŵer y system i'r eithaf ar gyfer y perfformiad uchaf posibl, gyda mwy o ddefnydd pŵer a sŵn posibl.",
  "This preset is designed to prioritize energy efficiency over performance. It sets power limits to conservative levels to reduce power consumption and heat generation, making it ideal for prolonged use in situations where maximizing battery life or minimizing energy usage is critical.": "Mae'r rhagosodiad hwn yn blaenoriaethu effeithlonrwydd ynni drwy osod terfynau pŵer ceidwadol i leihau defnydd pŵer a gwres.",
  "This preset aims to find a balance between performance and power consumption, providing a stable and efficient experience. This preset sets the power limits to a level that balances performance and power usage, without sacrificing too much of either.": "Mae'r rhagosodiad hwn yn cydbwyso perfformiad a defnydd pŵer i ddarparu profiad sefydlog ac effeithlon.",
  "Phantom Control Centre Now Available!": "Mae Phantom Control Centre Ar Gael Nawr!",
  "New Update Available!": "Diweddariad Newydd Ar Gael!",
  "Head to the settings menu to easily download the new Universal x86 Tuning Utility update!": "Ewch i'r ddewislen gosodiadau i lawrlwytho'r diweddariad Universal x86 Tuning Utility newydd!",
  "Charge Preset Applied!": "Rhagosodiad Gwefru wedi'i Gymhwyso!",
  "Your charge preset settings have been applied!": "Mae gosodiadau eich rhagosodiad gwefru wedi'u cymhwyso!",
  "Discharge Preset Applied!": "Rhagosodiad Dadwefru wedi'i Gymhwyso!",
  "Your discharge preset settings have been applied!": "Mae gosodiadau eich rhagosodiad dadwefru wedi'u cymhwyso!",
  "Resume Preset Applied!": "Rhagosodiad Ailddechrau wedi'i Gymhwyso!",
  "Your resume preset settings have been applied!": "Mae gosodiadau eich rhagosodiad ailddechrau wedi'u cymhwyso!",
  "Settings Reapplied!": "Gosodiadau wedi'u Hailgymhwyso!",
  "Your last applied settings have been reapplied!": "Mae eich gosodiadau diwethaf wedi'u hailgymhwyso!",
  "Performance Preset Applied!": "Rhagosodiad Perfformiad wedi'i Gymhwyso!",
  "The performance premade power preset has been applied!": "Mae'r rhagosodiad pŵer perfformiad wedi'i gymhwyso!",
  "Extreme Preset Applied!": "Rhagosodiad Eithafol wedi'i Gymhwyso!",
  "The extreme premade power preset has been applied!": "Mae'r rhagosodiad pŵer eithafol wedi'i gymhwyso!",
  "Eco Preset Applied!": "Rhagosodiad Economaidd wedi'i Gymhwyso!",
  "The eco premade power preset has been applied!": "Mae'r rhagosodiad pŵer economaidd wedi'i gymhwyso!",
  "Balanced Preset Applied!": "Rhagosodiad Cytbwys wedi'i Gymhwyso!",
  "The balanced premade power preset has been applied!": "Mae'r rhagosodiad pŵer cytbwys wedi'i gymhwyso!",
  "CPU Thermal Design Current (TDC) Limit (A)": "Terfyn Cerrynt Dylunio Thermol (TDC) CPU (A)",
  "CPU Electrical Design Current (EDC) Limit (A)": "Terfyn Cerrynt Dylunio Trydanol (EDC) CPU (A)",
  "System-on-Chip Thermal Design Current (TDC) Limit (A)": "Terfyn Cerrynt Dylunio Thermol (TDC) System-ar-Sglodyn (A)",
  "System-on-Chip Electrical Design Current (EDC) Limit (A)": "Terfyn Cerrynt Dylunio Trydanol (EDC) System-ar-Sglodyn (A)",
  "Integrated GPU Thermal Design Current (TDC) Limit (A)": "Terfyn Cerrynt Dylunio Thermol (TDC) GPU Integredig (A)",
  "Integrated GPU Electrical Design Current (EDC) Limit (A)": "Terfyn Cerrynt Dylunio Trydanol (EDC) GPU Integredig (A)",
  "Graphics Thermal Design Current (TDC) Limit (A)": "Terfyn Cerrynt Dylunio Thermol (TDC) Graffeg (A)",
  "Graphics Electrical Design Current (EDC) Limit (A)": "Terfyn Cerrynt Dylunio Trydanol (EDC) Graffeg (A)",
  "Precision Boost Overdrive (PBO) Scalar": "Lluosydd Precision Boost Overdrive (PBO)",
  "Provides the ability to set APU thermal targets.": "Yn galluogi gosod targedau thermol yr APU.",
  "Temperature Limit (°C)": "Terfyn Tymheredd (°C)",
  "Skin Temperature Limit (°C)": "Terfyn Tymheredd Arwyneb (°C)",
  "Provides the ability to set APU power targets.": "Yn galluogi gosod targedau pŵer yr APU.",
  "Provides the ability to set APU VRM current targets.": "Yn galluogi gosod targedau cerrynt modiwl rheoleiddiwr foltedd (VRM) yr APU.",
  "Controls the temperature limit at which the APU starts soft throttling": "Yn rheoli'r tymheredd lle mae'r APU yn dechrau cyfyngu'n raddol",
  "Controls the laptop chassis temperature limit at which the APU starts throttling": "Yn rheoli tymheredd siasi'r gliniadur lle mae'r APU yn dechrau cyfyngu",
  "Slow Power Limit (W)": "Terfyn Pŵer Araf (W)",
  "Slow Boost Duration (s)": "Hyd Hwb Araf (e)",
  "Fast Power Limit (W)": "Terfyn Pŵer Cyflym (W)",
  "Fast Boost Duration (s)": "Hyd Hwb Cyflym (e)",
  "Power Limit (W)": "Terfyn Pŵer (W)",
  "Power Limit 2 (W)": "Ail Derfyn Pŵer (W)",
  "Provides the ability to set CPU power targets.": "Yn galluogi gosod targedau pŵer y CPU.",
  "AC Controlled": "Rheolir gan AC",
  "Application Controlled": "Rheolir gan y rhaglen",
  "ASUS Power Profile": "Proffil Pŵer ASUS",
  "Auto Recapture": "Ail-ddal Awtomatig",
  "Auto recaptures the previous capture window after focus was lost and restored.": "Yn ail-ddal y ffenestr flaenorol ar ôl colli ac adfer ffocws.",
  "Auto Switch": "Newid Awtomatig",
  "Auto switch app profile": "Newid proffil rhaglen yn awtomatig",
  "Balanced (59%)": "Cytbwys (59%)",
  "Basic Adaptive Mode Settings": "Gosodiadau Sylfaenol y Modd Addasol",
  "Capture Sharpness (%)": "Miniogrwydd Dal (%)",
  "Controls the clock offset for your NVIDIA GPU\u0027s core clock": "Yn rheoli gwrthbwyso cloc craidd eich GPU NVIDIA",
  "Controls the clock offset for your NVIDIA GPU\u0027s VRAM clock": "Yn rheoli gwrthbwyso cloc VRAM eich GPU NVIDIA",
  "Controls the max negative curve optimiser limit adpative mode is allowed to set": "Yn rheoli\u0027r terfyn Optimeiddiwr Cromlin negatif mwyaf y gall y modd addasol ei osod",
  "Controls the max power limit adpative mode is allowed to set": "Yn rheoli\u0027r terfyn pŵer mwyaf y gall y modd addasol ei osod",
  "Controls the max temperature limit adaptive mode is allowed to set": "Yn rheoli\u0027r terfyn tymheredd mwyaf y gall y modd addasol ei osod",
  "Controls the maximum iGPU clock speed adaptive mode is allowed to set": "Yn rheoli\u0027r cloc iGPU mwyaf y gall y modd addasol ei osod",
  "Controls the maximum voltage your GPU will run within the Frequency/Voltage curve based on clock speed. You can undervolt your NVIDIA GPU by lowering this clock speed below stock and increasing the core clock offset. Start at your GPU\u0027s rated boost clock and work down. To reset it, set it to the maximum possible clock the slider allows.": "Yn rheoli foltedd mwyaf y GPU ar y gromlin Amledd/Foltedd. I danfoltio GPU NVIDIA, gostyngwch y cloc hwn o dan y gwerth safonol a chynyddwch wrthbwyso\u0027r craidd. Dechreuwch wrth y cloc hwb graddedig a gweithiwch i lawr. I ailosod, dewiswch gloc mwyaf y llithrydd.",
  "Controls the minimum CPU clock speed at which adaptive mode will start throttling iGPU clocks": "Yn rheoli\u0027r cloc CPU lleiaf lle bydd y modd addasol yn dechrau cyfyngu clociau\u0027r iGPU",
  "Controls the minimum iGPU clock speed adaptive mode is allowed to set": "Yn rheoli\u0027r cloc iGPU lleiaf y gall y modd addasol ei osod",
  "Controls the resolution of the window being captured. Use application controlled if you do not want UXTU to override the window resolution. Not all applications will be compatible with this mode!": "Yn rheoli cydraniad y ffenestr sy\u0027n cael ei dal. Dewiswch reolaeth gan y rhaglen os nad ydych am i UXTU ddiystyru\u0027r cydraniad. Nid yw pob rhaglen yn gydnaws â\u0027r modd hwn.",
  "Controls the set FPS limit in RTSS": "Yn rheoli\u0027r terfyn FPS a osodir yn RTSS",
  "Controls UXTU Super Resolution capture image sharpness.": "Yn rheoli miniogrwydd delwedd dal UXTU Super Resolution.",
  "Enable this preset for automatic switching. Can be used to exclude games/apps from auto switch.": "Galluogwch y rhagosodiad hwn ar gyfer newid awtomatig. Gellir ei ddefnyddio i eithrio gemau neu raglenni.",
  "Enable VSync": "Galluogi VSync",
  "Enables AMD Enhanced Sync within drivers on supported hardware.": "Yn galluogi AMD Enhanced Sync yn y gyrwyr ar galedwedd a gefnogir.",
  "Enables AMD Radeon™ Anti-Lag within drivers on supported hardware.": "Yn galluogi AMD Radeon™ Anti-Lag yn y gyrwyr ar galedwedd a gefnogir.",
  "Enables AMD Radeon™ Boost within drivers on supported hardware. Also allows you to set a minimum resolution in %.": "Yn galluogi AMD Radeon™ Boost ar galedwedd a gefnogir ac yn caniatáu gosod cydraniad lleiaf fel canran.",
  "Enables AMD Radeon™ Image Sharpening within drivers on supported hardware. Allows you to set a custom sharpness effect.": "Yn galluogi AMD Radeon™ Image Sharpening ac yn caniatáu gosod lefel miniogrwydd addasedig.",
  "Enables AMD Radeon™ Super Resolution within drivers on supported hardware. Also allows you to set a custom sharpness effect.": "Yn galluogi AMD Radeon™ Super Resolution ac yn caniatáu gosod lefel miniogrwydd addasedig.",
  "Enhanced Sync": "Cydamseru Gwell",
  "Frequency-Adjusted Voltage Limit (MHz)": "Terfyn Foltedd wedi\u0027i Addasu yn ôl Amledd (MHz)",
  "Games/Apps:": "Gemau/Rhaglenni:",
  "GPU Core Clock Offset (MHz)": "Gwrthbwyso Cloc Craidd GPU (MHz)",
  "GPU Memory Clock (MHz)": "Cloc Cof GPU (MHz)",
  "Max Curve Optimiser Limit (-)": "Terfyn Mwyaf yr Optimeiddiwr Cromlin (-)",
  "Max Power Limit (W)": "Terfyn Pŵer Mwyaf (W)",
  "Max Temperature Limit (°C)": "Terfyn Tymheredd Mwyaf (°C)",
  "Maximum iGPU Clock Limit (MHz)": "Terfyn Cloc iGPU Mwyaf (MHz)",
  "Minimum CPU Clock Limit (MHz)": "Terfyn Cloc CPU Lleiaf (MHz)",
  "Minimum iGPU Clock Limit (MHz)": "Terfyn Cloc iGPU Lleiaf (MHz)",
  "Notes: Ensure you balance CPU and iGPU clocks out for the best performance!": "Nodyn: Cydbwyswch glociau\u0027r CPU a\u0027r iGPU ar gyfer y perfformiad gorau!",
  "Notes: Wait for profiles to load before starting mode!": "Nodyn: Arhoswch i\u0027r proffiliau lwytho cyn cychwyn y modd!",
  "Performance (50%)": "Perfformiad (50%)",
  "Polling Rate": "Cyfradd Holi",
  "Powered by a customised version of Magpie. Use Alt+F to toggle.": "Wedi\u0027i bweru gan fersiwn addasedig o Magpie. Defnyddiwch Alt+F i\u0027w doglo.",
  "Provides the ability to customise driver graphics options": "Yn galluogi addasu dewisiadau graffeg y gyrrwr",
  "Provides the ability to set a custom RTSS frame limit.": "Yn galluogi gosod terfyn fframiau RTSS addasedig.",
  "Provides the ability to set an ASUS power profile. This will override Armoury Crate!": "Yn galluogi gosod proffil pŵer ASUS. Bydd hyn yn diystyru Armoury Crate!",
  "Provides the ability to set tune your NVIDIA GPU.": "Yn galluogi tiwnio eich GPU NVIDIA.",
  "Provides the ability to toggle/set adaptive mode targets.": "Yn galluogi toglo neu osod targedau\u0027r modd addasol.",
  "Provides the ability to toggle/set Turbo Boost Overdrive iGPU targets.": "Yn galluogi toglo neu osod targedau iGPU Turbo Boost Overdrive.",
  "Quality (67%)": "Ansawdd (67%)",
  "Radeon™ Anti-Lag": "Radeon™ Anti-Lag",
  "Radeon™ Boost (%)": "Radeon™ Boost (%)",
  "Radeon™ Image Sharpening (%)": "Miniogi Delwedd Radeon™ (%)",
  "Radeon™ Super Resolution (%)": "Cydraniad Uwch Radeon™ (%)",
  "Resolution Scale": "Graddfa Cydraniad",
  "RTSS Frame Limit (FPS)": "Terfyn Fframiau RTSS (FPS)",
  "Save current settings": "Cadw\u0027r gosodiadau cyfredol",
  "Silent": "Tawel",
  "Static RTSS Frame Rate": "Cyfradd Fframiau Statig RTSS",
  "Synchronises capture frame rate to display refresh rate.": "Yn cydamseru\u0027r gyfradd dal fframiau â chyfradd adnewyddu\u0027r dangosydd.",
  "Turbo": "Tyrbo",
  "Turbo Boost Overdrive iGPU Settings": "Gosodiadau iGPU Turbo Boost Overdrive",
  "Ultra Performance (33%)": "Perfformiad Uchel Iawn (33%)",
  "Ultra Quality (77%)": "Ansawdd Uchel Iawn (77%)",
  "Updates dropdown list with games/apps": "Yn diweddaru\u0027r rhestr gemau a rhaglenni",
  "UXTU Super Resolution": "Cydraniad Uwch UXTU",
  "Warning: We are not liable for any damages to hardware or resulting instabilities caused by adjustment of frequencies and voltages.": "Rhybudd: Nid ydym yn atebol am ddifrod i galedwedd nac ansefydlogrwydd a achosir gan addasu amleddau a folteddau.",
  "Apply a preset after the system resumes from sleep or hibernation.": "Cymhwyso rhagosodiad ar ôl i\u0027r system ailddechrau o gwsg neu aeafgysgu.",
  "Apply a preset whenever the battery begins charging.": "Cymhwyso rhagosodiad pan fydd y batri\u0027n dechrau gwefru.",
  "Apply a preset whenever the system begins running from battery power.": "Cymhwyso rhagosodiad pan fydd y system yn dechrau defnyddio pŵer batri.",
  "AutoOC: Adaptive CPU Undervolt": "AutoOC: Danfoltio CPU Addasol",
  "AutoOC: Adaptive iGPU Undervolt": "AutoOC: Danfoltio iGPU Addasol",
  "Dynamically optimises CPU voltage with built-in stability protection. Initial tuning may temporarily cause instability or crashes.": "Yn optimeiddio foltedd y CPU yn ddeinamig gyda diogelwch sefydlogrwydd. Gall y tiwnio cychwynnol achosi ansefydlogrwydd neu chwalfeydd dros dro.",
  "Dynamically optimises iGPU voltage with built-in stability protection. Initial tuning may temporarily cause instability or crashes.": "Yn optimeiddio foltedd yr iGPU yn ddeinamig gyda diogelwch sefydlogrwydd. Gall y tiwnio cychwynnol achosi ansefydlogrwydd neu chwalfeydd dros dro.",
  "None": "Dim",
  "25–100%": "25–100%",
  "50–200%": "50–200%",
  "Battery tile": "Teilsen batri",
  "Click the box and press the shortcut you want.": "Cliciwch y blwch a gwasgwch y llwybr byr rydych ei eisiau.",
  "CPU sensors": "Synwyryddion CPU",
  "Enable the game overlay and global shortcuts": "Galluogi\u0027r troshaen gêm a\u0027r llwybrau byr byd-eang",
  "FPS and low FPS values": "FPS a gwerthoedd FPS isel",
  "Frame-time values": "Gwerthoedd amser ffrâm",
  "GPU polling is completely disabled when this is off.": "Mae holi\u0027r GPU wedi\u0027i analluogi\u0027n llwyr pan fydd hwn wedi\u0027i ddiffodd.",
  "GPU sensors": "Synwyryddion GPU",
  "Keeps the overlay window ready without polling sensors.": "Yn cadw ffenestr y droshaen yn barod heb holi synwyryddion.",
  "Longer intervals reduce monitoring overhead.": "Mae cyfnodau hirach yn lleihau\u0027r gost fonitro.",
  "Memory usage": "Defnydd cof",
  "Rolling graphs": "Graffiau treigl",
  "Show or hide contents": "Dangos neu guddio cynnwys",
  "Show or hide overlay": "Dangos neu guddio\u0027r droshaen",
  "Show the overlay when UXTU starts": "Dangos y droshaen pan fydd UXTU yn cychwyn",
  "Copy": "Copïo",
  "Fan Control Test": "Prawf Rheoli Ffan",
  "Fan curve test": "Prawf cromlin ffan",
  "Set the requested fan speed as a percentage.": "Gosod cyflymder y ffan fel canran.",
  "Validate the loaded fan configuration and test direct fan-control commands.": "Dilysu\u0027r ffurfweddiad ffan a brofi gorchmynion rheoli uniongyrchol.",
  "PawnIO Driver Required": "Mae Angen Gyrrwr PawnIO",
  "PawnIO Driver Setup": "Gosod Gyrrwr PawnIO",
  "PawnIO is provided \u0027as is\u0027 without warranty of any kind, either express or implied. Use it at your own risk. The authors are not liable for damages arising from its use.": "Darperir PawnIO \u0027fel y mae\u0027 heb unrhyw warant. Defnyddiwch ef ar eich menter eich hun. Nid yw\u0027r awduron yn atebol am ddifrod sy\u0027n deillio o\u0027i ddefnyddio.",
  "The official PawnIO installer will handle installation. Administrator permission may be required.": "Bydd gosodwr swyddogol PawnIO yn trin y gosodiad. Efallai y bydd angen caniatâd gweinyddwr.",
  "This application requires the PawnIO driver to access supported low-level hardware features.": "Mae angen gyrrwr PawnIO ar y rhaglen hon i gyrchu nodweddion caledwedd lefel isel a gefnogir.",
  "This installer may be redistributed unmodified. Copyright © 2026 namazso \u003cadmin@namazso.eu\u003e.": "Gellir ailddosbarthu\u0027r gosodwr hwn heb ei addasu. Hawlfraint © 2026 namazso \u003cadmin@namazso.eu\u003e.",
  "Dashboard": "Dangosfwrdd",
  "Universal x86 Tuning Utility": "Universal x86 Tuning Utility",
  "V26.3.0 Beta 1": "V26.3.0 Beta 1",
  "Data": "Data",
  "False": "False",
  "UXTU Performance Overlay": "Troshaen Perfformiad UXTU",
  "Manual": "Â Llaw",
  "FPS": "FPS",
  "1% Low": "1% Isel",
  "0.1% Low": "0.1% Isel",
  "Frametime": "Amser Ffrâm",
  "1% ms": "1% ms",
  "0.1% ms": "0.1% ms",
  "API": "API",
  "Status": "Statws",
  "Time": "Amser",
  "Power": "Pŵer",
  "GPU": "GPU",
  "CPU": "CPU",
  "Frame Time (ms)": "Amser Ffrâm (ms)",
  "─ Frametime": "─ Amser Ffrâm",
  "─ 1% ms": "─ 1% ms",
  "─ 0.1% ms": "─ 0.1% ms",
  "Power (W)": "Pŵer (W)",
  "─ GPU Power": "─ Pŵer GPU",
  "─ CPU Power": "─ Pŵer CPU",
  "Note: Some output commands may not be compatible with RyzenAdj": "Nodyn: Efallai na fydd rhai gorchmynion allbwn yn gydnaws â RyzenAdj",
  "TEST TEST TEST": "PRAWF PRAWF PRAWF",
  "Caption": "Disgrifiad",
  "Instructions": "Cyfarwyddiadau",
  "L1 Cache": "Storfa L1",
  "L2 Cache": "Storfa L2",
  "L3 Cache": "Storfa L3",
  "Memory": "Cof",
  "Modules": "Modiwlau",
  "RAM Timings:": "Amseriadau RAM:",
  "Width": "Lled",
  "BGS:": "BGS:",
  "BGSA:": "BGSA:",
  "Cmd2T:": "Cmd2T:",
  "GDM:": "GDM:",
  "Preamble2T:": "Preamble2T:",
  "tCKE:": "tCKE:",
  "tCL:": "tCL:",
  "tCWL:": "tCWL:",
  "tFAW:": "tFAW:",
  "tFAWDLR:": "tFAWDLR:",
  "tFAWSLR:": "tFAWSLR:",
  "tMOD:": "tMOD:",
  "tMODPDA:": "tMODPDA:",
  "tMRD:": "tMRD:",
  "tMRDPDA:": "tMRDPDA:",
  "tPHYRDLAT:": "tPHYRDLAT:",
  "tPHYWRD:": "tPHYWRD:",
  "tPHYWRLAT:": "tPHYWRLAT:",
  "tRAS:": "tRAS:",
  "tRC:": "tRC:",
  "tRCDRD:": "tRCDRD:",
  "tRCDWR:": "tRCDWR:",
  "tRCPage:": "tRCPage:",
  "tRCPB:": "tRCPB:",
  "tRDDATA:": "tRDDATA:",
  "tRDRDBAN:": "tRDRDBAN:",
  "tRDRDDD:": "tRDRDDD:",
  "tRDRDSC:": "tRDRDSC:",
  "tRDRDSCDLR:": "tRDRDSCDLR:",
  "tRDRDSCL:": "tRDRDSCL:",
  "tRDRDSD:": "tRDRDSD:",
  "tRDWR:": "tRDWR:",
  "tREF:": "tREF:",
  "tREFCT:": "tREFCT:",
  "tRFC:": "tRFC:",
  "tRFC2:": "tRFC2:",
  "tRFC2CT:": "tRFC2CT:",
  "tRFC4:": "tRFC4:",
  "tRFC4CT:": "tRFC4CT:",
  "tRFCCT:": "tRFCCT:",
  "tRP:": "tRP:",
  "tRPPB:": "tRPPB:",
  "tRRDDLR:": "tRRDDLR:",
  "tRRDL:": "tRRDL:",
  "tRRDS:": "tRRDS:",
  "tRTP:": "tRTP:",
  "tSTAG:": "tSTAG:",
  "tSTAG2LR:": "tSTAG2LR:",
  "tSTAG4LR:": "tSTAG4LR:",
  "tSTAGLR:": "tSTAGLR:",
  "tWR:": "tWR:",
  "tWRMPR:": "tWRMPR:",
  "tWRRD:": "tWRRD:",
  "tWRRDSCDLR:": "tWRRDSCDLR:",
  "tWRWRBAN:": "tWRWRBAN:",
  "tWRWRDD:": "tWRWRDD:",
  "tWRWRSC:": "tWRWRSC:",
  "tWRWRSCDLR:": "tWRWRSCDLR:",
  "tWRWRSCL:": "tWRWRSCL:",
  "tWRWRSD:": "tWRWRSD:",
  "tWTRL:": "tWTRL:",
  "tWTRS:": "tWTRS:",
  "Allows control to change the Curve Optimiser Frequency/Voltage curve offset for core 1": "Yn caniatáu newid gwrthbwyso cromlin Amledd/Foltedd yr Optimeiddiwr Cromlin ar gyfer craidd 1",
  "Allows control to change the Curve Optimiser Frequency/Voltage curve offset for core 10": "Yn caniatáu newid gwrthbwyso cromlin Amledd/Foltedd yr Optimeiddiwr Cromlin ar gyfer craidd 10",
  "Allows control to change the Curve Optimiser Frequency/Voltage curve offset for core 11": "Yn caniatáu newid gwrthbwyso cromlin Amledd/Foltedd yr Optimeiddiwr Cromlin ar gyfer craidd 11",
  "Allows control to change the Curve Optimiser Frequency/Voltage curve offset for core 12": "Yn caniatáu newid gwrthbwyso cromlin Amledd/Foltedd yr Optimeiddiwr Cromlin ar gyfer craidd 12",
  "Allows control to change the Curve Optimiser Frequency/Voltage curve offset for core 2": "Yn caniatáu newid gwrthbwyso cromlin Amledd/Foltedd yr Optimeiddiwr Cromlin ar gyfer craidd 2",
  "Allows control to change the Curve Optimiser Frequency/Voltage curve offset for core 3": "Yn caniatáu newid gwrthbwyso cromlin Amledd/Foltedd yr Optimeiddiwr Cromlin ar gyfer craidd 3",
  "Allows control to change the Curve Optimiser Frequency/Voltage curve offset for core 4": "Yn caniatáu newid gwrthbwyso cromlin Amledd/Foltedd yr Optimeiddiwr Cromlin ar gyfer craidd 4",
  "Allows control to change the Curve Optimiser Frequency/Voltage curve offset for core 5": "Yn caniatáu newid gwrthbwyso cromlin Amledd/Foltedd yr Optimeiddiwr Cromlin ar gyfer craidd 5",
  "Allows control to change the Curve Optimiser Frequency/Voltage curve offset for core 6": "Yn caniatáu newid gwrthbwyso cromlin Amledd/Foltedd yr Optimeiddiwr Cromlin ar gyfer craidd 6",
  "Allows control to change the Curve Optimiser Frequency/Voltage curve offset for core 7": "Yn caniatáu newid gwrthbwyso cromlin Amledd/Foltedd yr Optimeiddiwr Cromlin ar gyfer craidd 7",
  "Allows control to change the Curve Optimiser Frequency/Voltage curve offset for core 8": "Yn caniatáu newid gwrthbwyso cromlin Amledd/Foltedd yr Optimeiddiwr Cromlin ar gyfer craidd 8",
  "Allows control to change the Curve Optimiser Frequency/Voltage curve offset for core 9": "Yn caniatáu newid gwrthbwyso cromlin Amledd/Foltedd yr Optimeiddiwr Cromlin ar gyfer craidd 9",
  "Controls the maximum soft clock target of the CPU. This only works when within your APUs specification.": "Yn rheoli targed cloc meddal Mwyaf CPU. Dim ond o fewn manyleb eich APU y mae hyn yn gweithio.",
  "Controls the maximum soft clock target of the Data Launch. This only works when within your APUs specification.": "Yn rheoli targed cloc meddal Mwyaf Lansio Data. Dim ond o fewn manyleb eich APU y mae hyn yn gweithio.",
  "Controls the maximum soft clock target of the iGPU. This only works when within your APUs specification.": "Yn rheoli targed cloc meddal Mwyaf iGPU. Dim ond o fewn manyleb eich APU y mae hyn yn gweithio.",
  "Controls the maximum soft clock target of the Infinity Fabric. This only works when within your APUs specification.": "Yn rheoli targed cloc meddal Mwyaf Infinity Fabric. Dim ond o fewn manyleb eich APU y mae hyn yn gweithio.",
  "Controls the maximum soft clock target of the SoC. This only works when within your APUs specification.": "Yn rheoli targed cloc meddal Mwyaf SoC. Dim ond o fewn manyleb eich APU y mae hyn yn gweithio.",
  "Controls the maximum soft clock target of the Video Core Next. This only works when within your APUs specification.": "Yn rheoli targed cloc meddal Mwyaf VCN. Dim ond o fewn manyleb eich APU y mae hyn yn gweithio.",
  "Controls the minimum soft clock target of the CPU. This only works when within your APUs specification.": "Yn rheoli targed cloc meddal Lleiaf CPU. Dim ond o fewn manyleb eich APU y mae hyn yn gweithio.",
  "Controls the minimum soft clock target of the Data Launch. This only works when within your APUs specification.": "Yn rheoli targed cloc meddal Lleiaf Lansio Data. Dim ond o fewn manyleb eich APU y mae hyn yn gweithio.",
  "Controls the minimum soft clock target of the iGPU. This only works when within your APUs specification.": "Yn rheoli targed cloc meddal Lleiaf iGPU. Dim ond o fewn manyleb eich APU y mae hyn yn gweithio.",
  "Controls the minimum soft clock target of the Infinity Fabric. This only works when within your APUs specification.": "Yn rheoli targed cloc meddal Lleiaf Infinity Fabric. Dim ond o fewn manyleb eich APU y mae hyn yn gweithio.",
  "Controls the minimum soft clock target of the SoC. This only works when within your APUs specification.": "Yn rheoli targed cloc meddal Lleiaf SoC. Dim ond o fewn manyleb eich APU y mae hyn yn gweithio.",
  "Controls the minimum soft clock target of the Video Core Next. This only works when within your APUs specification.": "Yn rheoli targed cloc meddal Lleiaf VCN. Dim ond o fewn manyleb eich APU y mae hyn yn gweithio.",
  "Core 1 Offset": "Gwrthbwyso Craidd 1",
  "Core 10 Offset": "Gwrthbwyso Craidd 10",
  "Core 11 Offset": "Gwrthbwyso Craidd 11",
  "Core 12 Offset": "Gwrthbwyso Craidd 12",
  "Core 2 Offset": "Gwrthbwyso Craidd 2",
  "Core 3 Offset": "Gwrthbwyso Craidd 3",
  "Core 4 Offset": "Gwrthbwyso Craidd 4",
  "Core 5 Offset": "Gwrthbwyso Craidd 5",
  "Core 6 Offset": "Gwrthbwyso Craidd 6",
  "Core 7 Offset": "Gwrthbwyso Craidd 7",
  "Core 8 Offset": "Gwrthbwyso Craidd 8",
  "Core 9 Offset": "Gwrthbwyso Craidd 9",
  "Core Group 1": "Grŵp Craidd 1",
  "Core Group 2": "Grŵp Craidd 2",
  "Core Group 3": "Grŵp Craidd 3",
  "Core Group 4": "Grŵp Craidd 4",
  "Core Group 5": "Grŵp Craidd 5",
  "Core Group 6": "Grŵp Craidd 6",
  "Core Group 7": "Grŵp Craidd 7",
  "Core Group 8": "Grŵp Craidd 8",
  "Soft Maximum CPU Clock (MHz)": "Cloc Meddal Mwyaf CPU (MHz)",
  "Soft Maximum Data Launch Clock (MHz)": "Cloc Meddal Mwyaf Lansio Data (MHz)",
  "Soft Maximum iGPU Clock (MHz)": "Cloc Meddal Mwyaf iGPU (MHz)",
  "Soft Maximum Infinity Fabric Clock (MHz)": "Cloc Meddal Mwyaf Infinity Fabric (MHz)",
  "Soft Maximum SoC Clock (MHz)": "Cloc Meddal Mwyaf SoC (MHz)",
  "Soft Maximum VCN Clock (MHz)": "Cloc Meddal Mwyaf VCN (MHz)",
  "Soft Minimum CPU Clock (MHz)": "Cloc Meddal Lleiaf CPU (MHz)",
  "Soft Minimum Data Launch Clock (MHz)": "Cloc Meddal Lleiaf Lansio Data (MHz)",
  "Soft Minimum iGPU Clock (MHz)": "Cloc Meddal Lleiaf iGPU (MHz)",
  "Soft Minimum Infinity Fabric Clock (MHz)": "Cloc Meddal Lleiaf Infinity Fabric (MHz)",
  "Soft Minimum SoC Clock (MHz)": "Cloc Meddal Lleiaf SoC (MHz)",
  "Soft Minimum VCN Clock (MHz)": "Cloc Meddal Lleiaf VCN (MHz)",
  "All CCDs": "Pob CCD",
  "All Core Offset": "Gwrthbwyso Pob Craidd",
  "Allows control to change the all core Curve Optimiser Frequency/Voltage curve offset": "Yn caniatáu newid gwrthbwyso cromlin Amledd/Foltedd yr Optimeiddiwr Cromlin ar gyfer pob craidd",
  "Allows control to change the iGPU Curve Optimiser Frequency/Voltage curve offset": "Yn caniatáu newid gwrthbwyso cromlin Amledd/Foltedd Optimeiddiwr Cromlin yr iGPU",
  "Allows control to change the PBO Scalar which adjusts the FIT/FITness/FailuresInTime limit by the set amount": "Yn caniatáu newid lluosydd PBO, sy\u0027n addasu terfyn FIT yn ôl y swm a osodir",
  "AMD Boost Profile": "Proffil Hwb AMD",
  "AMD Per-Core Curve Optimiser (CCD1)": "Optimeiddiwr Cromlin AMD fesul Craidd (CCD1)",
  "AMD Per-Core Curve Optimiser (CCD2)": "Optimeiddiwr Cromlin AMD fesul Craidd (CCD2)",
  "APU Soft Clock Limit Tuning": "Tiwnio Terfynau Cloc Meddal APU",
  "ASUS GPU Ultimate Mode": "Modd GPU Ultimate ASUS",
  "ASUS iGPU Only Mode": "Modd iGPU yn Unig ASUS",
  "Best Performance": "Perfformiad Gorau",
  "Best Power Effciency": "Effeithlonrwydd Pŵer Gorau",
  "Cache Offset (mV)": "Gwrthbwyso Storfa (mV)",
  "CCD 0": "CCD 0",
  "CCD 1": "CCD 1",
  "CCD Affinity Mode": "Modd Perthynas Core Complex Die (CCD)",
  "Controls how long the APU stays within the fast boost power limit": "Yn rheoli pa mor hir y mae\u0027r APU yn aros o fewn y terfyn pŵer hwb cyflym",
  "Controls how long the APU stays within the slow boost power limit": "Yn rheoli pa mor hir y mae\u0027r APU yn aros o fewn y terfyn pŵer hwb araf",
  "Controls the APU\u0027s fast boost duration power limit. Within SmartShift enabled systems, this options controls the total power shared between the AMD CPU and AMD dGPU": "Yn rheoli terfyn pŵer hwb cyflym yr APU. Ar systemau SmartShift, mae hwn yn rheoli cyfanswm y pŵer a rennir rhwng CPU AMD a dGPU AMD",
  "Controls the APU\u0027s Skin Temperature Aware Power Management power limit": "Yn rheoli terfyn pŵer Rheoli Pŵer sy\u0027n Ymwybodol o Dymheredd Arwyneb (STAPM) yr APU",
  "Controls the APU\u0027s slow boost duration power limit. Within SmartShift enabled systems, this options controls the total power shared between the AMD CPU and AMD dGPU": "Yn rheoli terfyn pŵer hwb araf yr APU. Ar systemau SmartShift, mae hwn yn rheoli cyfanswm y pŵer a rennir rhwng CPU AMD a dGPU AMD",
  "Controls the CPU\u0027s Electrical Design Current limit": "Yn rheoli terfyn Cerrynt Dylunio Trydanol (EDC) y CPU",
  "Controls the CPU\u0027s Package Power Tracking power limit": "Yn rheoli terfyn Tracio Pŵer Pecyn (PPT) y CPU",
  "Controls the CPU\u0027s short boost power limit": "Yn rheoli terfyn pŵer hwb byr y CPU",
  "Controls the CPU\u0027s Thermal Design Current limit": "Yn rheoli terfyn Cerrynt Dylunio Thermol (TDC) y CPU",
  "Controls the CPU\u0027s total power limit": "Yn rheoli cyfanswm terfyn pŵer y CPU",
  "Controls the iGPU\u0027s Electrical Design Current limit": "Yn rheoli terfyn Cerrynt Dylunio Trydanol (EDC) yr iGPU",
  "Controls the iGPU\u0027s Thermal Design Current limit": "Yn rheoli terfyn Cerrynt Dylunio Thermol (TDC) yr iGPU",
  "Controls the maximum soft clock target of the Data Launch Clock. This only works when within your APUs specification.": "Yn rheoli targed cloc meddal mwyaf y Cloc Lansio Data. Dim ond o fewn manyleb eich APU y mae hyn yn gweithio.",
  "Controls the minimum soft clock target of the Data Launch Clock. This only works when within your APUs specification.": "Yn rheoli targed cloc meddal lleiaf y Cloc Lansio Data. Dim ond o fewn manyleb eich APU y mae hyn yn gweithio.",
  "Controls the power limit for your NVIDIA GPU": "Yn rheoli terfyn pŵer eich GPU NVIDIA",
  "Controls the set voltage for the CPU": "Yn rheoli\u0027r foltedd a osodir ar gyfer y CPU",
  "Controls the SoC\u0027s Electrical Design Current limit": "Yn rheoli terfyn Cerrynt Dylunio Trydanol (EDC) y System-ar-Sglodyn",
  "Controls the SoC\u0027s Thermal Design Current limit": "Yn rheoli terfyn Cerrynt Dylunio Thermol (TDC) y System-ar-Sglodyn",
  "Controls the static boost clock speed of the iGPU, requires either a system reboot or system sleep to revert back to normal.": "Yn rheoli cloc hwb sefydlog yr iGPU. Mae angen ailgychwyn y system neu ei rhoi i gysgu i ddychwelyd i\u0027r arfer.",
  "Controls the temperature limit at which the CPU starts hard throttling": "Yn rheoli\u0027r tymheredd lle mae\u0027r CPU yn dechrau cyfyngu\u0027n galed",
  "Core Offset (mV)": "Gwrthbwyso Craidd (mV)",
  "CPU Balance": "Cydbwysedd CPU",
  "CPU Clocks (MHz)": "Clociau CPU (MHz)",
  "CPU EDC Limit (A)": "Terfyn Cerrynt Dylunio Trydanol (EDC) CPU (A)",
  "CPU TDC Limit (A)": "Terfyn Cerrynt Dylunio Thermol (TDC) CPU (A)",
  "CPU VID (mV)": "VID CPU (mV)",
  "CustomPresets": "Rhagosodiadau Addasedig",
  "Directs threads to selected CCDs, trimming cross-die traffic and fine-tuning performance.": "Yn cyfeirio edafedd at CCDau penodol, gan leihau traffig rhwng deiau a mireinio perfformiad.",
  "EDC Limit (A)": "Terfyn Cerrynt Dylunio Trydanol (EDC) (A)",
  "GFX EDC Limit (A)": "Terfyn Cerrynt Dylunio Trydanol (EDC) Graffeg (A)",
  "GFX TDC Limit (A)": "Terfyn Cerrynt Dylunio Thermol (TDC) Graffeg (A)",
  "GPU Balance": "Cydbwysedd GPU",
  "GPU Memory Clock Offset (MHz)": "Gwrthbwyso Cloc Cof GPU (MHz)",
  "GPU Power Limit (W)": "Terfyn Pŵer GPU (W)",
  "iGPU Clock (MHz)": "Cloc iGPU (MHz)",
  "iGPU Offset": "Gwrthbwyso iGPU",
  "iGPU Offset (mV)": "Gwrthbwyso iGPU (mV)",
  "PBO Scalar": "Lluosydd Precision Boost Overdrive (PBO)",
  "Power Saving": "Arbed Pŵer",
  "PPT Limit (W)": "Terfyn Tracio Pŵer Pecyn (PPT) (W)",
  "Provides the ability to change the Windows power mode from a preset.": "Yn galluogi newid modd pŵer Windows o ragosodiad.",
  "Provides the ability to customise Curve Optimiser options.": "Yn galluogi addasu dewisiadau Optimeiddiwr Cromlin.",
  "Provides the ability to customise PBO options.": "Yn galluogi addasu dewisiadau Precision Boost Overdrive (PBO).",
  "Provides the ability to customise per-core Curve Optimiser options.": "Yn galluogi addasu dewisiadau Optimeiddiwr Cromlin fesul craidd.",
  "Provides the ability to manually toggle MUX switch on/off. This will override Armoury Crate!": "Yn galluogi toglo switsh MUX â llaw. Bydd hyn yn diystyru Armoury Crate!",
  "Provides the ability to set a custom supported display refresh rate. May not work for everyone!": "Yn galluogi gosod cyfradd adnewyddu addasedig a gefnogir. Efallai na fydd yn gweithio i bawb!",
  "Provides the ability to set a manual boost profile which impact on boost delay.": "Yn galluogi gosod proffil hwb â llaw sy\u0027n effeithio ar oedi hwb.",
  "Provides the ability to set a static CPU clock": "Yn galluogi gosod cloc CPU sefydlog",
  "Provides the ability to set a static iGPU boost clock on select APUs/CPUs.": "Yn galluogi gosod cloc hwb iGPU sefydlog ar APUau neu CPUau penodol.",
  "Provides the ability to set CPU thermal targets.": "Yn galluogi gosod targedau thermol y CPU.",
  "Provides the ability to set tune your AMD Ryzen™ CPU.": "Yn galluogi tiwnio eich CPU AMD Ryzen™.",
  "Provides the ability to set various soft clock speed targets on select APUs.": "Yn galluogi gosod gwahanol dargedau cloc meddal ar APUau penodol.",
  "Provides the ability to toggle iGPU only mode on/off. This will override Armoury Crate!": "Yn galluogi toglo modd iGPU yn unig. Bydd hyn yn diystyru Armoury Crate!",
  "Provides the ability to tune the clock ratios of your Intel CPU based the number of cores actively in use.": "Yn galluogi tiwnio cymarebau cloc CPU Intel yn ôl nifer y creiddiau sy\u0027n cael eu defnyddio.",
  "Provides the ability to tune the power balance of your Intel CPU.": "Yn galluogi tiwnio cydbwysedd pŵer eich CPU Intel.",
  "Provides the ability to tune the voltages of your Intel CPU.": "Yn galluogi tiwnio folteddau eich CPU Intel.",
  "Provides the ability to tune your NVIDIA GPU.": "Yn galluogi tiwnio eich GPU NVIDIA.",
  "SoC EDC Limit (A)": "Terfyn Cerrynt Dylunio Trydanol (EDC) System-ar-Sglodyn (A)",
  "SoC TDC Limit (A)": "Terfyn Cerrynt Dylunio Thermol (TDC) System-ar-Sglodyn (A)",
  "STAPM Power Limit (W)": "Terfyn Rheoli Pŵer sy\u0027n Ymwybodol o Dymheredd Arwyneb (STAPM) (W)",
  "System Agent Offset (mV)": "Gwrthbwyso Asiant System (mV)",
  "System Controlled": "Dan Reolaeth y System",
  "TDC Limit (A)": "Terfyn Cerrynt Dylunio Thermol (TDC) (A)",
  "Disabling GPU Ultimate Mode requires a restart to take effect!": "Mae angen ailgychwyn ar ôl analluogi Modd GPU Ultimate!",
  "Full Charge: {0} mAh | Design: {1} mAh": "Gwefr Lawn: {0} mAh | Dyluniad: {1} mAh",
  "GPU Ultimate Mode": "Modd GPU Ultimate",
  "NVIDIA GPU Warning": "Rhybudd GPU NVIDIA",
  "Premade Presets - Framework Laptop 13 (AMD Ryzen 7040U Series)": "Rhagosodiadau Parod - Framework Laptop 13 (Cyfres AMD Ryzen 7040U)",
  "Premade Presets - Framework Laptop 16 (AMD Ryzen 7040HS Series)": "Rhagosodiadau Parod - Framework Laptop 16 (Cyfres AMD Ryzen 7040HS)",
  "ROP count is lower than expected on {0} ({1} ROPs out of {2} ROPs)": "Mae {0} yn dangos diffyg ROP ({1} ROP allan o {2})",
  "Switching the GPU to Ultimate Mode requires a restart to take effect!": "Mae angen ailgychwyn ar ôl newid y GPU i Fodd Ultimate!",
  "This should only take a few moments!": "Dylai hyn gymryd ychydig eiliadau yn unig!",
  "Worked!": "Wedi gweithio!",
  "{0}% charging": "{0}% yn gwefru",
  "Charging": "Yn gwefru",
  "Discharging": "Yn dadwefru",
  "No battery": "Dim batri",
  "Restart": "Ailgychwyn"
}
